wfastcgi.py
wfastcgi-2.2.1.dist-info/DESCRIPTION.rst
wfastcgi-2.2.1.dist-info/METADATA
wfastcgi-2.2.1.dist-info/RECORD
wfastcgi-2.2.1.dist-info/WHEEL
wfastcgi-2.2.1.dist-info/entry_points.txt
wfastcgi-2.2.1.dist-info/metadata.json
wfastcgi-2.2.1.dist-info/top_level.txt
