Metadata-Version: 1.1
Name: wfastcgi
Version: 2.2.1
Summary: An IIS-Python bridge based on WSGI and FastCGI.
Home-page: http://aka.ms/PTVS
Author: Microsoft Corporation
Author-email: ptvshelp@microsoft.com
License: Apache License 2.0
Keywords: iis fastcgi wsgi windows server mod_python
Platform: UNKNOWN
Classifier: Development Status :: 6 - Mature
Classifier: License :: OSI Approved :: Apache Software License
Classifier: Operating System :: Microsoft :: Windows
Classifier: Programming Language :: Python :: 2
Classifier: Programming Language :: Python :: 2.7
Classifier: Programming Language :: Python :: 3
Classifier: Programming Language :: Python :: 3.3
Classifier: Programming Language :: Python :: 3.4
Classifier: Programming Language :: Python :: 3.5
Classifier: Topic :: Internet
Classifier: Topic :: Internet :: WWW/HTTP
Classifier: Topic :: Internet :: WWW/HTTP :: WSGI
Classifier: Topic :: Internet :: WWW/HTTP :: WSGI :: Server
